LICENSE
MANIFEST.in
README.md
grymt.py
setup.py
grymt.egg-info/PKG-INFO
grymt.egg-info/SOURCES.txt
grymt.egg-info/dependency_links.txt
grymt.egg-info/entry_points.txt
grymt.egg-info/requires.txt
grymt.egg-info/top_level.txt