Metadata-Version: 1.1
Name: grymt
Version: 1.2
Summary: Preps a set of HTML files for deployment
Home-page: https://github.com/peterbe/grymt
Author: Peter Bengtsson
Author-email: mail@peterbe.com
License: MPL2
Keywords: grymt,deploy,deployment,minification,concatenation
Platform: UNKNOWN
Classifier: Intended Audience :: Developers
Classifier: Intended Audience :: System Administrators
Classifier: License :: OSI Approved :: Mozilla Public License 2.0 (MPL 2.0)
Classifier: Programming Language :: Python :: 2
Classifier: Topic :: Software Development :: Build Tools
Classifier: Topic :: System :: Installation/Setup
Classifier: Topic :: System :: Systems Administration
